MANIFEST.in
Pipfile
Pipfile.lock
README.md
pyproject.toml
requirements-prod.txt
requirements-subpackages.txt
setup-venv.sh
setup.cfg
setup.py
rkd.core.egg-info/PKG-INFO
rkd.core.egg-info/SOURCES.txt
rkd.core.egg-info/dependency_links.txt
rkd.core.egg-info/requires.txt
rkd.core.egg-info/top_level.txt
rkd/core/__init__.py
rkd/core/__main__.py
rkd/core/aliasgroups.py
rkd/core/audit.py
rkd/core/bootstrap.py
rkd/core/context.py
rkd/core/contract.py
rkd/core/env.py
rkd/core/exception.py
rkd/core/inputoutput.py
rkd/core/packaging.py
rkd/core/resolver.py
rkd/core/syntax.py
rkd/core/taskutil.py
rkd/core/test.py
rkd/core/validator.py
rkd/core/yaml_context.py
rkd/core/yaml_parser.py
rkd/core/api/__init__.py
rkd/core/api/contract.py
rkd/core/api/inputoutput.py
rkd/core/api/parsing.py
rkd/core/api/syntax.py
rkd/core/api/temp.py
rkd/core/api/testing.py
rkd/core/argparsing/__init__.py
rkd/core/argparsing/blocks.py
rkd/core/argparsing/model.py
rkd/core/argparsing/parser.py
rkd/core/execution/__init__.py
rkd/core/execution/declarative.py
rkd/core/execution/executor.py
rkd/core/execution/results.py
rkd/core/execution/serialization.py
rkd/core/misc/banner.txt
rkd/core/misc/initial-structure/setup-venv.sh
rkd/core/misc/initial-structure/.rkd/makefile.py
rkd/core/misc/initial-structure/.rkd/makefile.yaml
rkd/core/misc/initial-structure/.rkd/logs/.gitkeep
rkd/core/misc/internal/makefile.py
rkd/core/misc/internal/schema/org.riotkit.rkd-yaml-v1.json
rkd/core/standardlib/__init__.py
rkd/core/standardlib/core.py
rkd/core/standardlib/env.py
rkd/core/standardlib/jinja.py
rkd/core/standardlib/shell.py